<launch4jConfig>
  <dontWrapJar>true</dontWrapJar>
  <headerType>gui</headerType>
  <jar>lib/tapaal.jar</jar>
  <outfile>/Users/srba/Dropbox/TAPAAL/Release-2.4/tapaal.exe</outfile>
  <errTitle></errTitle>
  <cmdLine></cmdLine>
  <chdir></chdir>
  <priority>normal</priority>
  <downloadUrl>http://java.com/download</downloadUrl>
  <supportUrl>http://www.tapaal.net</supportUrl>
  <customProcName>false</customProcName>
  <stayAlive>false</stayAlive>
  <manifest></manifest>
  <icon>/Users/srba/Dropbox/TAPAAL/Icon/tapaal-2-4.ico</icon>
  <classPath>
    <mainClass>TAPAAL</mainClass>
    <cp>lib/*</cp>
  </classPath>
  <jre>
    <path></path>
    <minVersion>1.6.0</minVersion>
    <maxVersion></maxVersion>
    <jdkPreference>preferJre</jdkPreference>
  </jre>
  <versionInfo>
    <fileVersion>2.4.0.0</fileVersion>
    <txtFileVersion>2.4.0.0</txtFileVersion>
    <fileDescription>TAPAAL</fileDescription>
    <copyright>TAPAAL Team 2008-2013</copyright>
    <productVersion>2.4.0.0</productVersion>
    <txtProductVersion>2.4.0.0</txtProductVersion>
    <productName>TAPAAL</productName>
    <companyName></companyName>
    <internalName>tapaal</internalName>
    <originalFilename>tapaal.exe</originalFilename>
  </versionInfo>
</launch4jConfig>